README.md
setup.cfg
setup.py
zig_pdist/Binomialdistribution.py
zig_pdist/Gaussiandistribution.py
zig_pdist/Generaldistribution.py
zig_pdist/__init__.py
zig_pdist.egg-info/PKG-INFO
zig_pdist.egg-info/SOURCES.txt
zig_pdist.egg-info/dependency_links.txt
zig_pdist.egg-info/not-zip-safe
zig_pdist.egg-info/top_level.txt